pytrials/__init__.py
pytrials/client.py
pytrials/fields.csv
pytrials/utils.py
pytrials-1.0.0.dist-info/AUTHORS.rst
pytrials-1.0.0.dist-info/LICENSE
pytrials-1.0.0.dist-info/METADATA
pytrials-1.0.0.dist-info/WHEEL
pytrials-1.0.0.dist-info/top_level.txt
pytrials-1.0.0.dist-info/RECORD
