Metadata-Version: 2.1
Name: pytrials
Version: 1.0.0
Summary: Python wrapper around the clinicaltrials.gov API
Home-page: https://github.com/jvfe/pytrials
Author: João Vitor F. Cavalcante
Author-email: jvfe@ufrn.edu.br
License: BSD license
Keywords: pytrials clinical-trials clinical trials tabular text-mining text opendata
Classifier: Development Status :: 2 - Pre-Alpha
Classifier: Intended Audience :: Developers
Classifier: License :: OSI Approved :: BSD License
Classifier: Natural Language :: English
Classifier: Programming Language :: Python :: 3
Classifier: Programming Language :: Python :: 3.7
Classifier: Programming Language :: Python :: 3.8
Classifier: Programming Language :: Python :: 3.9
Requires-Python: >=3.7
License-File: LICENSE
License-File: AUTHORS.rst
